CHANGES.rst
MANIFEST.in
README.rst
setup.cfg
setup.py
khufu_opinion/__init__.py
khufu_opinion/paster.py
khufu_opinion.egg-info/PKG-INFO
khufu_opinion.egg-info/SOURCES.txt
khufu_opinion.egg-info/dependency_links.txt
khufu_opinion.egg-info/entry_points.txt
khufu_opinion.egg-info/not-zip-safe
khufu_opinion.egg-info/requires.txt
khufu_opinion.egg-info/top_level.txt
khufu_opinion/paster_template/+project+.wsgi_tmpl
khufu_opinion/paster_template/CHANGES.rst_tmpl
khufu_opinion/paster_template/MANIFEST.in_tmpl
khufu_opinion/paster_template/README.rst_tmpl
khufu_opinion/paster_template/development.ini_tmpl
khufu_opinion/paster_template/setup.py_tmpl
khufu_opinion/paster_template/+package+/__init__.py_tmpl
khufu_opinion/paster_template/+package+/manage.py_tmpl
khufu_opinion/paster_template/+package+/models.py_tmpl
khufu_opinion/paster_template/+package+/resources.py_tmpl
khufu_opinion/paster_template/+package+/tests.py_tmpl
khufu_opinion/paster_template/+package+/views.py_tmpl
khufu_opinion/paster_template/+package+/static/favicon.ico
khufu_opinion/paster_template/+package+/static/footerbg.png
khufu_opinion/paster_template/+package+/static/headerbg.png
khufu_opinion/paster_template/+package+/static/ie6.css
khufu_opinion/paster_template/+package+/static/middlebg.png
khufu_opinion/paster_template/+package+/static/pylons.css
khufu_opinion/paster_template/+package+/static/pyramid-small.png
khufu_opinion/paster_template/+package+/static/pyramid.png
khufu_opinion/paster_template/+package+/static/transparent.gif
khufu_opinion/paster_template/+package+/templates/default.jinja2
khufu_opinion/paster_template/+package+/templates/layout.jinja2