Metadata-Version: 1.0
Name: khufu-opinion
Version: 0.5
Summary: Set of paster templates for rapid Pyramid development
Home-page: https://github.com/khufuproject/khufu_opinion
Author: Rocky Burt
Author-email: rocky@serverzen.com
License: BSD
Keywords: wsgi pylons pyramid sqlalchemy khufu jinja2
Platform: UNKNOWN
Classifier: License :: OSI Approved :: BSD License
Classifier: Intended Audience :: Developers
Classifier: Programming Language :: Python
Classifier: Topic :: Internet :: WWW/HTTP :: WSGI
